[
  {
    "reqId": "Req28626",
    "firstName": "Donny",
    "fullName": "Donny Kielt",
    "rating": "3",
    "comment": "vestibulum proin eu mi nulla ac enim in tempor turpis nec euismod",
    "email": "dkielt0@spiegel.de",
    "submissionDate": "7/25/2021",
    "status": "Closed",
    "country": "Russia"
  },
  {
    "reqId": "Req01928",
    "firstName": "Betta",
    "fullName": "Betta Winnett",
    "rating": "5",
    "comment": "nisl nunc nisl duis bibendum felis sed interdum venenatis turpis enim blandit mi in porttitor",
    "email": "bwinnett1@buzzfeed.com",
    "submissionDate": "3/17/2021",
    "status": "New",
    "country": "Russia"
  },
  {
    "reqId": "Req29829",
    "firstName": "Andrew",
    "fullName": "Andrew Towey",
    "rating": "5",
    "comment": "maecenas pulvinar lobortis est phasellus sit amet erat nulla tempus vivamus in felis eu sapien cursus",
    "email": "atowey2@joomla.org",
    "submissionDate": "12/30/2020",
    "status": "Closed",
    "country": "Ukraine"
  },
  {
    "reqId": "Req00675",
    "firstName": "Ashton",
    "fullName": "Ashton Baxill",
    "rating": "1",
    "comment": "dolor quis odio consequat varius integer ac leo pellentesque ultrices",
    "email": "abaxill3@ed.gov",
    "submissionDate": "3/3/2021",
    "status": "In Review",
    "country": "Russia"
  },
  {
    "reqId": "Req15836",
    "firstName": "Helene",
    "fullName": "Helene Cowin",
    "rating": "1",
    "comment": "commodo placerat praesent blandit nam nulla integer pede justo lacinia",
    "email": "hcowin4@naver.com",
    "submissionDate": "2/2/2021",
    "status": "In Review",
    "country": "Russia"
  },
  {
    "reqId": "Req86058",
    "firstName": "Prue",
    "fullName": "Prue Dentith",
    "rating": "4",
    "comment": "amet cursus id turpis integer aliquet massa id lobortis convallis tortor risus dapibus augue",
    "email": "pdentith5@com.com",
    "submissionDate": "8/26/2021",
    "status": "New",
    "country": "Russia"
  },
  {
    "reqId": "Req77830",
    "firstName": "Celestyna",
    "fullName": "Celestyna Skoughman",
    "rating": "4",
    "comment": "interdum in ante vestibulum ante ipsum primis in faucibus orci luctus et ultrices posuere cubilia curae duis faucibus",
    "email": "cskoughman6@odnoklassniki.ru",
    "submissionDate": "5/28/2021",
    "status": "In Review",
    "country": "Russia"
  },
  {
    "reqId": "Req96578",
    "firstName": "Wilie",
    "fullName": "Wilie Ormrod",
    "rating": "5",
    "comment": "et eros vestibulum ac est lacinia nisi venenatis tristique fusce congue diam id ornare imperdiet sapien urna pretium nisl ut",
    "email": "wormrod7@technorati.com",
    "submissionDate": "6/15/2021",
    "status": "In Review",
    "country": "Ukraine"
  },
  {
    "reqId": "Req86897",
    "firstName": "Halette",
    "fullName": "Halette Kentish",
    "rating": "4",
    "comment": "nec nisi volutpat eleifend donec ut dolor morbi vel lectus in quam fringilla rhoncus",
    "email": "hkentish8@icq.com",
    "submissionDate": "11/26/2020",
    "status": "New",
    "country": "Ukraine"
  },
  {
    "reqId": "Req20976",
    "firstName": "Mari",
    "fullName": "Mari Merrell",
    "rating": "5",
    "comment": "in blandit ultrices enim lorem ipsum dolor sit amet consectetuer adipiscing elit",
    "email": "mmerrell9@cisco.com",
    "submissionDate": "9/16/2021",
    "status": "Closed",
    "country": "Ukraine"
  },
  {
    "reqId": "Req77571",
    "firstName": "Fritz",
    "fullName": "Fritz Mellows",
    "rating": "4",
    "comment": "pellentesque viverra pede ac diam cras pellentesque volutpat dui maecenas tristique est et tempus semper est quam pharetra magna ac",
    "email": "fmellowsa@ucsd.edu",
    "submissionDate": "7/15/2021",
    "status": "In Review",
    "country": "Russia"
  },
  {
    "reqId": "Req21132",
    "firstName": "Griz",
    "fullName": "Griz Mallinar",
    "rating": "5",
    "comment": "pede malesuada in imperdiet et commodo vulputate justo in blandit ultrices enim",
    "email": "gmallinarb@example.com",
    "submissionDate": "9/21/2021",
    "status": "New",
    "country": "Russia"
  },
  {
    "reqId": "Req06295",
    "firstName": "Jean",
    "fullName": "Jean McEachern",
    "rating": "2",
    "comment": "magna vestibulum aliquet ultrices erat tortor sollicitudin mi sit amet lobortis sapien sapien non mi integer ac neque duis",
    "email": "jmceachernc@toplist.cz",
    "submissionDate": "1/6/2021",
    "status": "In Review",
    "country": "Russia"
  },
  {
    "reqId": "Req89070",
    "firstName": "Sibyl",
    "fullName": "Sibyl Waison",
    "rating": "4",
    "comment": "cubilia curae duis faucibus accumsan odio curabitur convallis duis consequat dui nec nisi volutpat eleifend",
    "email": "swaisond@eventbrite.com",
    "submissionDate": "8/23/2021",
    "status": "In Review",
    "country": "Russia"
  },
  {
    "reqId": "Req29360",
    "firstName": "Sascha",
    "fullName": "Sascha McIlvoray",
    "rating": "2",
    "comment": "at turpis donec posuere metus vitae ipsum aliquam non mauris morbi non lectus aliquam sit amet diam in magna",
    "email": "smcilvoraye@e-recht24.de",
    "submissionDate": "8/15/2021",
    "status": "In Review",
    "country": "Russia"
  },
  {
    "reqId": "Req98504",
    "firstName": "Leora",
    "fullName": "Leora Bendik",
    "rating": "3",
    "comment": "hendrerit at vulputate vitae nisl aenean lectus pellentesque eget nunc donec quis orci eget orci vehicula condimentum curabitur",
    "email": "lbendikf@networkadvertising.org",
    "submissionDate": "12/26/2020",
    "status": "In Review",
    "country": "Russia"
  },
  {
    "reqId": "Req41009",
    "firstName": "Tessa",
    "fullName": "Tessa MacWhirter",
    "rating": "1",
    "comment": "quisque erat eros viverra eget congue eget semper rutrum nulla",
    "email": "tmacwhirterg@i2i.jp",
    "submissionDate": "5/31/2021",
    "status": "Closed",
    "country": "Russia"
  },
  {
    "reqId": "Req17555",
    "firstName": "Nigel",
    "fullName": "Nigel Jouen",
    "rating": "1",
    "comment": "vel lectus in quam fringilla rhoncus mauris enim leo rhoncus sed vestibulum sit amet",
    "email": "njouenh@cargocollective.com",
    "submissionDate": "1/18/2021",
    "status": "In Review",
    "country": "Ukraine"
  },
  {
    "reqId": "Req98736",
    "firstName": "Glen",
    "fullName": "Glen Yurkevich",
    "rating": "2",
    "comment": "ipsum dolor sit amet consectetuer adipiscing elit proin interdum mauris non",
    "email": "gyurkevichi@google.ca",
    "submissionDate": "12/4/2020",
    "status": "Closed",
    "country": "Russia"
  },
  {
    "reqId": "Req85217",
    "firstName": "Juliann",
    "fullName": "Juliann McGuiney",
    "rating": "1",
    "comment": "felis donec semper sapien a libero nam dui proin leo",
    "email": "jmcguineyj@abc.net.au",
    "submissionDate": "11/8/2021",
    "status": "In Review",
    "country": "Russia"
  },
  {
    "reqId": "Req72892",
    "firstName": "Anny",
    "fullName": "Anny Crohan",
    "rating": "3",
    "comment": "lectus in quam fringilla rhoncus mauris enim leo rhoncus sed vestibulum sit amet",
    "email": "acrohank@elegantthemes.com",
    "submissionDate": "4/18/2021",
    "status": "New",
    "country": "Russia"
  },
  {
    "reqId": "Req08837",
    "firstName": "Arlyne",
    "fullName": "Arlyne Mussen",
    "rating": "2",
    "comment": "auctor sed tristique in tempus sit amet sem fusce consequat nulla nisl nunc nisl",
    "email": "amussenl@drupal.org",
    "submissionDate": "7/28/2021",
    "status": "New",
    "country": "Russia"
  },
  {
    "reqId": "Req87875",
    "firstName": "Heriberto",
    "fullName": "Heriberto Valti",
    "rating": "1",
    "comment": "sagittis sapien cum sociis natoque penatibus et magnis dis parturient montes nascetur ridiculus mus etiam vel augue vestibulum",
    "email": "hvaltim@sogou.com",
    "submissionDate": "3/4/2021",
    "status": "Closed",
    "country": "Ukraine"
  },
  {
    "reqId": "Req81301",
    "firstName": "Jessika",
    "fullName": "Jessika Ainge",
    "rating": "2",
    "comment": "vel ipsum praesent blandit lacinia erat vestibulum sed magna at nunc",
    "email": "jaingen@deviantart.com",
    "submissionDate": "12/25/2020",
    "status": "In Review",
    "country": "Ukraine"
  },
  {
    "reqId": "Req46791",
    "firstName": "Gray",
    "fullName": "Gray Stute",
    "rating": "3",
    "comment": "nulla sed accumsan felis ut at dolor quis odio consequat varius",
    "email": "gstuteo@cpanel.net",
    "submissionDate": "3/3/2021",
    "status": "Closed",
    "country": "Russia"
  },
  {
    "reqId": "Req57623",
    "firstName": "Saleem",
    "fullName": "Saleem Dibdin",
    "rating": "1",
    "comment": "luctus et ultrices posuere cubilia curae duis faucibus accumsan odio curabitur convallis duis consequat dui nec",
    "email": "sdibdinp@theguardian.com",
    "submissionDate": "8/6/2021",
    "status": "New",
    "country": "Russia"
  },
  {
    "reqId": "Req05204",
    "firstName": "Andy",
    "fullName": "Andy McAless",
    "rating": "3",
    "comment": "morbi non lectus aliquam sit amet diam in magna bibendum imperdiet nullam orci pede",
    "email": "amcalessq@over-blog.com",
    "submissionDate": "11/16/2020",
    "status": "Closed",
    "country": "Russia"
  },
  {
    "reqId": "Req66417",
    "firstName": "Joanna",
    "fullName": "Joanna Loren",
    "rating": "1",
    "comment": "at nunc commodo placerat praesent blandit nam nulla integer pede justo lacinia eget tincidunt eget tempus",
    "email": "jlorenr@ucla.edu",
    "submissionDate": "2/3/2021",
    "status": "In Review",
    "country": "Ukraine"
  },
  {
    "reqId": "Req77610",
    "firstName": "Ferd",
    "fullName": "Ferd Heliet",
    "rating": "5",
    "comment": "orci pede venenatis non sodales sed tincidunt eu felis fusce posuere felis sed lacus morbi sem mauris laoreet ut",
    "email": "fheliets@usa.gov",
    "submissionDate": "4/3/2021",
    "status": "Closed",
    "country": "Ukraine"
  },
  {
    "reqId": "Req45578",
    "firstName": "Chrissy",
    "fullName": "Chrissy Barbier",
    "rating": "1",
    "comment": "felis sed interdum venenatis turpis enim blandit mi in porttitor pede justo eu massa donec dapibus duis",
    "email": "cbarbiert@yolasite.com",
    "submissionDate": "7/1/2021",
    "status": "In Review",
    "country": "Russia"
  },
  {
    "reqId": "Req47425",
    "firstName": "Odelle",
    "fullName": "Odelle Trodden",
    "rating": "1",
    "comment": "nisl venenatis lacinia aenean sit amet justo morbi ut odio cras mi pede malesuada in imperdiet",
    "email": "otroddenu@phpbb.com",
    "submissionDate": "5/5/2021",
    "status": "New",
    "country": "Russia"
  },
  {
    "reqId": "Req69394",
    "firstName": "Millisent",
    "fullName": "Millisent Scandred",
    "rating": "1",
    "comment": "nulla neque libero convallis eget eleifend luctus ultricies eu nibh quisque id justo sit",
    "email": "mscandredv@google.es",
    "submissionDate": "10/20/2021",
    "status": "Closed",
    "country": "Russia"
  },
  {
    "reqId": "Req55359",
    "firstName": "Morgun",
    "fullName": "Morgun Olliver",
    "rating": "4",
    "comment": "sapien varius ut blandit non interdum in ante vestibulum ante ipsum",
    "email": "molliverw@state.gov",
    "submissionDate": "9/30/2021",
    "status": "In Review",
    "country": "Russia"
  },
  {
    "reqId": "Req61006",
    "firstName": "Alair",
    "fullName": "Alair Bricksey",
    "rating": "3",
    "comment": "justo sollicitudin ut suscipit a feugiat et eros vestibulum ac est lacinia nisi venenatis tristique",
    "email": "abrickseyx@china.com.cn",
    "submissionDate": "5/3/2021",
    "status": "New",
    "country": "Ukraine"
  },
  {
    "reqId": "Req19619",
    "firstName": "Christy",
    "fullName": "Christy Going",
    "rating": "4",
    "comment": "libero nullam sit amet turpis elementum ligula vehicula consequat morbi a ipsum integer a nibh in quis justo",
    "email": "cgoingy@parallels.com",
    "submissionDate": "6/4/2021",
    "status": "Closed",
    "country": "Russia"
  },
  {
    "reqId": "Req24526",
    "firstName": "Raimundo",
    "fullName": "Raimundo Marrill",
    "rating": "5",
    "comment": "vitae nisl aenean lectus pellentesque eget nunc donec quis orci eget orci vehicula",
    "email": "rmarrillz@weebly.com",
    "submissionDate": "5/4/2021",
    "status": "New",
    "country": "Russia"
  },
  {
    "reqId": "Req59917",
    "firstName": "Abigail",
    "fullName": "Abigail Lindstrom",
    "rating": "5",
    "comment": "adipiscing elit proin risus praesent lectus vestibulum quam sapien varius ut blandit non interdum in ante vestibulum ante ipsum",
    "email": "alindstrom10@tumblr.com",
    "submissionDate": "2/21/2021",
    "status": "In Review",
    "country": "Russia"
  },
  {
    "reqId": "Req14431",
    "firstName": "Winfred",
    "fullName": "Winfred Syer",
    "rating": "1",
    "comment": "diam id ornare imperdiet sapien urna pretium nisl ut volutpat sapien arcu sed augue",
    "email": "wsyer11@mozilla.org",
    "submissionDate": "3/6/2021",
    "status": "New",
    "country": "Russia"
  },
  {
    "reqId": "Req75914",
    "firstName": "Darcy",
    "fullName": "Darcy Espinola",
    "rating": "4",
    "comment": "pede posuere nonummy integer non velit donec diam neque vestibulum eget vulputate ut ultrices vel augue vestibulum ante",
    "email": "despinola12@wikia.com",
    "submissionDate": "5/27/2021",
    "status": "In Review",
    "country": "Russia"
  },
  {
    "reqId": "Req72806",
    "firstName": "Courtney",
    "fullName": "Courtney Humberstone",
    "rating": "4",
    "comment": "eu magna vulputate luctus cum sociis natoque penatibus et magnis dis parturient montes",
    "email": "chumberstone13@japanpost.jp",
    "submissionDate": "3/30/2021",
    "status": "New",
    "country": "Russia"
  },
  {
    "reqId": "Req53413",
    "firstName": "Liesa",
    "fullName": "Liesa Rigmand",
    "rating": "5",
    "comment": "elementum in hac habitasse platea dictumst morbi vestibulum velit id pretium iaculis diam erat fermentum justo nec condimentum",
    "email": "lrigmand14@fastcompany.com",
    "submissionDate": "6/3/2021",
    "status": "New",
    "country": "Ukraine"
  },
  {
    "reqId": "Req95937",
    "firstName": "Trudi",
    "fullName": "Trudi Coulsen",
    "rating": "4",
    "comment": "sed tristique in tempus sit amet sem fusce consequat nulla nisl",
    "email": "tcoulsen15@cnn.com",
    "submissionDate": "7/28/2021",
    "status": "In Review",
    "country": "Russia"
  },
  {
    "reqId": "Req28013",
    "firstName": "Giustina",
    "fullName": "Giustina Scade",
    "rating": "3",
    "comment": "duis bibendum morbi non quam nec dui luctus rutrum nulla",
    "email": "gscade16@weebly.com",
    "submissionDate": "5/2/2021",
    "status": "In Review",
    "country": "Russia"
  },
  {
    "reqId": "Req27606",
    "firstName": "Thorndike",
    "fullName": "Thorndike Dot",
    "rating": "4",
    "comment": "donec vitae nisi nam ultrices libero non mattis pulvinar nulla pede ullamcorper augue a suscipit nulla",
    "email": "tdot17@sitemeter.com",
    "submissionDate": "3/21/2021",
    "status": "New",
    "country": "Russia"
  },
  {
    "reqId": "Req11779",
    "firstName": "Lydie",
    "fullName": "Lydie Rizzello",
    "rating": "3",
    "comment": "est donec odio justo sollicitudin ut suscipit a feugiat et eros vestibulum ac est lacinia nisi venenatis",
    "email": "lrizzello18@accuweather.com",
    "submissionDate": "11/28/2020",
    "status": "Closed",
    "country": "Russia"
  },
  {
    "reqId": "Req52363",
    "firstName": "Shurwood",
    "fullName": "Shurwood Flowitt",
    "rating": "1",
    "comment": "lacus curabitur at ipsum ac tellus semper interdum mauris ullamcorper purus sit amet nulla quisque arcu",
    "email": "sflowitt19@facebook.com",
    "submissionDate": "12/6/2020",
    "status": "New",
    "country": "Russia"
  },
  {
    "reqId": "Req65757",
    "firstName": "Helyn",
    "fullName": "Helyn Hatz",
    "rating": "2",
    "comment": "in lectus pellentesque at nulla suspendisse potenti cras in purus eu magna vulputate luctus cum sociis natoque penatibus",
    "email": "hhatz1a@usgs.gov",
    "submissionDate": "4/29/2021",
    "status": "In Review",
    "country": "Russia"
  },
  {
    "reqId": "Req29649",
    "firstName": "Dalia",
    "fullName": "Dalia Vida",
    "rating": "4",
    "comment": "sapien a libero nam dui proin leo odio porttitor id consequat in consequat ut nulla sed accumsan felis ut at",
    "email": "dvida1b@ucla.edu",
    "submissionDate": "9/27/2021",
    "status": "Closed",
    "country": "Russia"
  },
  {
    "reqId": "Req02045",
    "firstName": "Kittie",
    "fullName": "Kittie Sharratt",
    "rating": "3",
    "comment": "nisi volutpat eleifend donec ut dolor morbi vel lectus in quam fringilla rhoncus",
    "email": "ksharratt1c@odnoklassniki.ru",
    "submissionDate": "7/5/2021",
    "status": "New",
    "country": "Russia"
  },
  {
    "reqId": "Req64699",
    "firstName": "Cynthea",
    "fullName": "Cynthea Coom",
    "rating": "1",
    "comment": "luctus et ultrices posuere cubilia curae mauris viverra diam vitae quam suspendisse potenti",
    "email": "ccoom1d@surveymonkey.com",
    "submissionDate": "5/17/2021",
    "status": "Closed",
    "country": "Russia"
  },
  {
    "reqId": "Req32213",
    "firstName": "Danell",
    "fullName": "Danell Sherrin",
    "rating": "5",
    "comment": "id pretium iaculis diam erat fermentum justo nec condimentum neque",
    "email": "dsherrin1e@mac.com",
    "submissionDate": "2/28/2021",
    "status": "In Review",
    "country": "Russia"
  },
  {
    "reqId": "Req93897",
    "firstName": "Isa",
    "fullName": "Isa Dyhouse",
    "rating": "4",
    "comment": "magnis dis parturient montes nascetur ridiculus mus vivamus vestibulum sagittis sapien cum sociis natoque penatibus et magnis dis parturient montes",
    "email": "idyhouse1f@google.it",
    "submissionDate": "4/4/2021",
    "status": "New",
    "country": "Ukraine"
  },
  {
    "reqId": "Req19940",
    "firstName": "Rebeka",
    "fullName": "Rebeka Vettore",
    "rating": "4",
    "comment": "ligula in lacus curabitur at ipsum ac tellus semper interdum mauris ullamcorper purus sit amet nulla",
    "email": "rvettore1g@usatoday.com",
    "submissionDate": "4/30/2021",
    "status": "Closed",
    "country": "Russia"
  },
  {
    "reqId": "Req81748",
    "firstName": "Nevsa",
    "fullName": "Nevsa Armor",
    "rating": "5",
    "comment": "velit vivamus vel nulla eget eros elementum pellentesque quisque porta volutpat erat quisque erat eros viverra eget congue eget",
    "email": "narmor1h@virginia.edu",
    "submissionDate": "1/16/2021",
    "status": "In Review",
    "country": "Russia"
  },
  {
    "reqId": "Req77028",
    "firstName": "Millicent",
    "fullName": "Millicent Egar",
    "rating": "1",
    "comment": "gravida sem praesent id massa id nisl venenatis lacinia aenean sit amet justo morbi ut odio cras mi pede",
    "email": "megar1i@abc.net.au",
    "submissionDate": "8/12/2021",
    "status": "New",
    "country": "Russia"
  },
  {
    "reqId": "Req23900",
    "firstName": "Ruthie",
    "fullName": "Ruthie Rathbourne",
    "rating": "3",
    "comment": "eu magna vulputate luctus cum sociis natoque penatibus et magnis dis parturient montes nascetur ridiculus mus vivamus vestibulum sagittis",
    "email": "rrathbourne1j@jimdo.com",
    "submissionDate": "9/2/2021",
    "status": "Closed",
    "country": "Russia"
  },
  {
    "reqId": "Req61556",
    "firstName": "Auria",
    "fullName": "Auria Huggon",
    "rating": "4",
    "comment": "lorem id ligula suspendisse ornare consequat lectus in est risus",
    "email": "ahuggon1k@naver.com",
    "submissionDate": "6/18/2021",
    "status": "New",
    "country": "Ukraine"
  },
  {
    "reqId": "Req42915",
    "firstName": "Daffi",
    "fullName": "Daffi Kobes",
    "rating": "3",
    "comment": "hac habitasse platea dictumst aliquam augue quam sollicitudin vitae consectetuer eget rutrum at lorem integer",
    "email": "dkobes1l@cyberchimps.com",
    "submissionDate": "3/9/2021",
    "status": "In Review",
    "country": "Ukraine"
  },
  {
    "reqId": "Req38212",
    "firstName": "Louisette",
    "fullName": "Louisette Roxby",
    "rating": "3",
    "comment": "platea dictumst etiam faucibus cursus urna ut tellus nulla ut erat id mauris vulputate elementum nullam varius nulla",
    "email": "lroxby1m@gov.uk",
    "submissionDate": "8/9/2021",
    "status": "In Review",
    "country": "Russia"
  },
  {
    "reqId": "Req64747",
    "firstName": "Darren",
    "fullName": "Darren Struan",
    "rating": "4",
    "comment": "at nulla suspendisse potenti cras in purus eu magna vulputate luctus cum sociis natoque penatibus",
    "email": "dstruan1n@domainmarket.com",
    "submissionDate": "8/10/2021",
    "status": "In Review",
    "country": "Russia"
  },
  {
    "reqId": "Req32549",
    "firstName": "Genna",
    "fullName": "Genna Press",
    "rating": "1",
    "comment": "neque libero convallis eget eleifend luctus ultricies eu nibh quisque id justo sit amet sapien dignissim vestibulum vestibulum ante ipsum",
    "email": "gpress1o@irs.gov",
    "submissionDate": "4/18/2021",
    "status": "Closed",
    "country": "Russia"
  },
  {
    "reqId": "Req27595",
    "firstName": "Stefanie",
    "fullName": "Stefanie Lindborg",
    "rating": "3",
    "comment": "aliquam lacus morbi quis tortor id nulla ultrices aliquet maecenas leo odio condimentum id",
    "email": "slindborg1p@about.com",
    "submissionDate": "11/21/2020",
    "status": "New",
    "country": "Russia"
  },
  {
    "reqId": "Req33841",
    "firstName": "Willey",
    "fullName": "Willey Tackley",
    "rating": "5",
    "comment": "nunc proin at turpis a pede posuere nonummy integer non velit donec diam neque vestibulum eget vulputate",
    "email": "wtackley1q@joomla.org",
    "submissionDate": "4/28/2021",
    "status": "Closed",
    "country": "Russia"
  },
  {
    "reqId": "Req96514",
    "firstName": "Dulce",
    "fullName": "Dulce Whitlam",
    "rating": "2",
    "comment": "lectus vestibulum quam sapien varius ut blandit non interdum in ante vestibulum ante",
    "email": "dwhitlam1r@xinhuanet.com",
    "submissionDate": "12/24/2020",
    "status": "Closed",
    "country": "Russia"
  },
  {
    "reqId": "Req55843",
    "firstName": "Rickey",
    "fullName": "Rickey Jeandot",
    "rating": "4",
    "comment": "diam vitae quam suspendisse potenti nullam porttitor lacus at turpis donec posuere metus vitae ipsum aliquam",
    "email": "rjeandot1s@ustream.tv",
    "submissionDate": "12/31/2020",
    "status": "Closed",
    "country": "Russia"
  },
  {
    "reqId": "Req31746",
    "firstName": "Robinette",
    "fullName": "Robinette Kropach",
    "rating": "4",
    "comment": "quis orci nullam molestie nibh in lectus pellentesque at nulla suspendisse potenti",
    "email": "rkropach1t@businessweek.com",
    "submissionDate": "1/12/2021",
    "status": "In Review",
    "country": "Russia"
  },
  {
    "reqId": "Req12551",
    "firstName": "Elmo",
    "fullName": "Elmo Taggerty",
    "rating": "2",
    "comment": "lacinia aenean sit amet justo morbi ut odio cras mi",
    "email": "etaggerty1u@theglobeandmail.com",
    "submissionDate": "8/11/2021",
    "status": "New",
    "country": "Russia"
  },
  {
    "reqId": "Req47456",
    "firstName": "Hayyim",
    "fullName": "Hayyim Faustin",
    "rating": "3",
    "comment": "lorem ipsum dolor sit amet consectetuer adipiscing elit proin interdum mauris non ligula pellentesque ultrices phasellus id sapien in",
    "email": "hfaustin1v@google.ru",
    "submissionDate": "8/12/2021",
    "status": "In Review",
    "country": "Russia"
  },
  {
    "reqId": "Req57840",
    "firstName": "Cathe",
    "fullName": "Cathe Keenleyside",
    "rating": "1",
    "comment": "dignissim vestibulum vestibulum ante ipsum primis in faucibus orci luctus et",
    "email": "ckeenleyside1w@chicagotribune.com",
    "submissionDate": "7/20/2021",
    "status": "Closed",
    "country": "Ukraine"
  },
  {
    "reqId": "Req99760",
    "firstName": "Danika",
    "fullName": "Danika Proschke",
    "rating": "4",
    "comment": "non pretium quis lectus suspendisse potenti in eleifend quam a odio in hac habitasse platea dictumst maecenas",
    "email": "dproschke1x@go.com",
    "submissionDate": "11/6/2021",
    "status": "Closed",
    "country": "Russia"
  },
  {
    "reqId": "Req82118",
    "firstName": "Sandye",
    "fullName": "Sandye Ackroyd",
    "rating": "5",
    "comment": "ut at dolor quis odio consequat varius integer ac leo",
    "email": "sackroyd1y@sitemeter.com",
    "submissionDate": "10/1/2021",
    "status": "Closed",
    "country": "Russia"
  },
  {
    "reqId": "Req98745",
    "firstName": "Kennie",
    "fullName": "Kennie Spafford",
    "rating": "1",
    "comment": "sociis natoque penatibus et magnis dis parturient montes nascetur ridiculus mus etiam vel augue vestibulum rutrum rutrum neque aenean auctor",
    "email": "kspafford1z@apple.com",
    "submissionDate": "12/4/2020",
    "status": "Closed",
    "country": "Ukraine"
  },
  {
    "reqId": "Req68377",
    "firstName": "Lorrin",
    "fullName": "Lorrin Foxwell",
    "rating": "3",
    "comment": "odio justo sollicitudin ut suscipit a feugiat et eros vestibulum ac est lacinia nisi venenatis",
    "email": "lfoxwell20@gravatar.com",
    "submissionDate": "5/5/2021",
    "status": "Closed",
    "country": "Russia"
  },
  {
    "reqId": "Req70540",
    "firstName": "Gabrielle",
    "fullName": "Gabrielle Tattersill",
    "rating": "4",
    "comment": "diam id ornare imperdiet sapien urna pretium nisl ut volutpat sapien arcu sed augue",
    "email": "gtattersill21@exblog.jp",
    "submissionDate": "8/3/2021",
    "status": "New",
    "country": "Ukraine"
  },
  {
    "reqId": "Req31562",
    "firstName": "Nickolas",
    "fullName": "Nickolas McBeth",
    "rating": "4",
    "comment": "at feugiat non pretium quis lectus suspendisse potenti in eleifend quam a odio in hac habitasse platea",
    "email": "nmcbeth22@tripadvisor.com",
    "submissionDate": "12/22/2020",
    "status": "In Review",
    "country": "Russia"
  },
  {
    "reqId": "Req75982",
    "firstName": "Dionisio",
    "fullName": "Dionisio Kingsley",
    "rating": "4",
    "comment": "tempus semper est quam pharetra magna ac consequat metus sapien ut nunc vestibulum ante ipsum primis in faucibus",
    "email": "dkingsley23@wsj.com",
    "submissionDate": "3/3/2021",
    "status": "Closed",
    "country": "Russia"
  },
  {
    "reqId": "Req91326",
    "firstName": "Gill",
    "fullName": "Gill Davidovici",
    "rating": "3",
    "comment": "justo etiam pretium iaculis justo in hac habitasse platea dictumst etiam faucibus cursus",
    "email": "gdavidovici24@ox.ac.uk",
    "submissionDate": "5/24/2021",
    "status": "In Review",
    "country": "Russia"
  },
  {
    "reqId": "Req81035",
    "firstName": "Faustina",
    "fullName": "Faustina Harby",
    "rating": "1",
    "comment": "habitasse platea dictumst aliquam augue quam sollicitudin vitae consectetuer eget rutrum at lorem integer tincidunt ante vel",
    "email": "fharby25@ameblo.jp",
    "submissionDate": "7/25/2021",
    "status": "New",
    "country": "Russia"
  },
  {
    "reqId": "Req75452",
    "firstName": "Elnore",
    "fullName": "Elnore Ribchester",
    "rating": "5",
    "comment": "turpis eget elit sodales scelerisque mauris sit amet eros suspendisse accumsan tortor quis turpis sed ante",
    "email": "eribchester26@desdev.cn",
    "submissionDate": "2/17/2021",
    "status": "Closed",
    "country": "Russia"
  },
  {
    "reqId": "Req90217",
    "firstName": "Allix",
    "fullName": "Allix Habbin",
    "rating": "4",
    "comment": "bibendum imperdiet nullam orci pede venenatis non sodales sed tincidunt eu felis fusce posuere",
    "email": "ahabbin27@state.gov",
    "submissionDate": "2/15/2021",
    "status": "Closed",
    "country": "Russia"
  },
  {
    "reqId": "Req88391",
    "firstName": "Terri",
    "fullName": "Terri Killner",
    "rating": "1",
    "comment": "integer ac leo pellentesque ultrices mattis odio donec vitae nisi nam ultrices libero",
    "email": "tkillner28@flavors.me",
    "submissionDate": "10/24/2021",
    "status": "In Review",
    "country": "Russia"
  },
  {
    "reqId": "Req72730",
    "firstName": "Jeth",
    "fullName": "Jeth Natt",
    "rating": "4",
    "comment": "in quis justo maecenas rhoncus aliquam lacus morbi quis tortor",
    "email": "jnatt29@domainmarket.com",
    "submissionDate": "8/1/2021",
    "status": "New",
    "country": "Russia"
  },
  {
    "reqId": "Req76350",
    "firstName": "Flo",
    "fullName": "Flo Wiffield",
    "rating": "5",
    "comment": "magna vestibulum aliquet ultrices erat tortor sollicitudin mi sit amet lobortis sapien",
    "email": "fwiffield2a@exblog.jp",
    "submissionDate": "5/1/2021",
    "status": "New",
    "country": "Russia"
  },
  {
    "reqId": "Req16341",
    "firstName": "Tannie",
    "fullName": "Tannie O'Hallihane",
    "rating": "3",
    "comment": "facilisi cras non velit nec nisi vulputate nonummy maecenas tincidunt lacus at",
    "email": "tohallihane2b@so-net.ne.jp",
    "submissionDate": "12/3/2020",
    "status": "In Review",
    "country": "Ukraine"
  },
  {
    "reqId": "Req54502",
    "firstName": "Justinian",
    "fullName": "Justinian Toplin",
    "rating": "3",
    "comment": "non mauris morbi non lectus aliquam sit amet diam in magna bibendum imperdiet",
    "email": "jtoplin2c@usatoday.com",
    "submissionDate": "1/29/2021",
    "status": "Closed",
    "country": "Russia"
  },
  {
    "reqId": "Req67616",
    "firstName": "Samara",
    "fullName": "Samara Auld",
    "rating": "1",
    "comment": "pulvinar sed nisl nunc rhoncus dui vel sem sed sagittis nam congue risus semper porta",
    "email": "sauld2d@blogspot.com",
    "submissionDate": "8/21/2021",
    "status": "In Review",
    "country": "Russia"
  },
  {
    "reqId": "Req00956",
    "firstName": "Sig",
    "fullName": "Sig Pottell",
    "rating": "1",
    "comment": "in eleifend quam a odio in hac habitasse platea dictumst maecenas ut massa quis augue luctus tincidunt nulla mollis molestie",
    "email": "spottell2e@nhs.uk",
    "submissionDate": "8/21/2021",
    "status": "Closed",
    "country": "Russia"
  },
  {
    "reqId": "Req06946",
    "firstName": "Ulrica",
    "fullName": "Ulrica Dunkley",
    "rating": "2",
    "comment": "arcu adipiscing molestie hendrerit at vulputate vitae nisl aenean lectus",
    "email": "udunkley2f@cmu.edu",
    "submissionDate": "2/18/2021",
    "status": "New",
    "country": "Russia"
  },
  {
    "reqId": "Req10960",
    "firstName": "Donal",
    "fullName": "Donal Heninghem",
    "rating": "5",
    "comment": "aenean lectus pellentesque eget nunc donec quis orci eget orci vehicula condimentum curabitur in libero ut massa volutpat",
    "email": "dheninghem2g@stumbleupon.com",
    "submissionDate": "1/25/2021",
    "status": "In Review",
    "country": "Russia"
  },
  {
    "reqId": "Req34677",
    "firstName": "Elaine",
    "fullName": "Elaine Huddart",
    "rating": "4",
    "comment": "viverra eget congue eget semper rutrum nulla nunc purus phasellus in felis",
    "email": "ehuddart2h@zdnet.com",
    "submissionDate": "12/3/2020",
    "status": "Closed",
    "country": "Russia"
  },
  {
    "reqId": "Req50398",
    "firstName": "Theresa",
    "fullName": "Theresa Petrik",
    "rating": "5",
    "comment": "libero nullam sit amet turpis elementum ligula vehicula consequat morbi a ipsum integer a",
    "email": "tpetrik2i@hhs.gov",
    "submissionDate": "9/2/2021",
    "status": "In Review",
    "country": "Russia"
  },
  {
    "reqId": "Req57824",
    "firstName": "Imojean",
    "fullName": "Imojean Langstone",
    "rating": "2",
    "comment": "amet eleifend pede libero quis orci nullam molestie nibh in lectus pellentesque at nulla suspendisse potenti cras",
    "email": "ilangstone2j@loc.gov",
    "submissionDate": "8/23/2021",
    "status": "New",
    "country": "Russia"
  },
  {
    "reqId": "Req85899",
    "firstName": "Matias",
    "fullName": "Matias Maddie",
    "rating": "1",
    "comment": "morbi vel lectus in quam fringilla rhoncus mauris enim leo rhoncus sed vestibulum sit amet",
    "email": "mmaddie2k@blogs.com",
    "submissionDate": "2/7/2021",
    "status": "In Review",
    "country": "Russia"
  },
  {
    "reqId": "Req83431",
    "firstName": "Herman",
    "fullName": "Herman Spring",
    "rating": "5",
    "comment": "vulputate elementum nullam varius nulla facilisi cras non velit nec nisi vulputate nonummy",
    "email": "hspring2l@skyrock.com",
    "submissionDate": "5/29/2021",
    "status": "Closed",
    "country": "Russia"
  },
  {
    "reqId": "Req80676",
    "firstName": "Kermie",
    "fullName": "Kermie Finlow",
    "rating": "2",
    "comment": "adipiscing elit proin interdum mauris non ligula pellentesque ultrices phasellus id sapien in",
    "email": "kfinlow2m@ed.gov",
    "submissionDate": "10/30/2021",
    "status": "In Review",
    "country": "Russia"
  },
  {
    "reqId": "Req52790",
    "firstName": "Lenci",
    "fullName": "Lenci Dyos",
    "rating": "4",
    "comment": "sed sagittis nam congue risus semper porta volutpat quam pede lobortis ligula sit amet eleifend pede libero quis orci",
    "email": "ldyos2n@facebook.com",
    "submissionDate": "6/7/2021",
    "status": "In Review",
    "country": "Russia"
  },
  {
    "reqId": "Req26361",
    "firstName": "Ambrosio",
    "fullName": "Ambrosio Gunthorpe",
    "rating": "1",
    "comment": "dis parturient montes nascetur ridiculus mus vivamus vestibulum sagittis sapien cum sociis natoque penatibus et magnis dis",
    "email": "agunthorpe2o@uol.com.br",
    "submissionDate": "12/3/2020",
    "status": "Closed",
    "country": "Russia"
  },
  {
    "reqId": "Req93295",
    "firstName": "Lenard",
    "fullName": "Lenard Eriksson",
    "rating": "2",
    "comment": "cras mi pede malesuada in imperdiet et commodo vulputate justo in",
    "email": "leriksson2p@bandcamp.com",
    "submissionDate": "6/21/2021",
    "status": "Closed",
    "country": "Russia"
  },
  {
    "reqId": "Req28026",
    "firstName": "Odelia",
    "fullName": "Odelia Warstall",
    "rating": "2",
    "comment": "suspendisse accumsan tortor quis turpis sed ante vivamus tortor duis",
    "email": "owarstall2q@businessweek.com",
    "submissionDate": "2/7/2021",
    "status": "Closed",
    "country": "Russia"
  },
  {
    "reqId": "Req85524",
    "firstName": "Cristal",
    "fullName": "Cristal Gallegos",
    "rating": "4",
    "comment": "risus dapibus augue vel accumsan tellus nisi eu orci mauris lacinia sapien quis",
    "email": "cgallegos2r@ycombinator.com",
    "submissionDate": "5/9/2021",
    "status": "In Review",
    "country": "Russia"
  }
]
